ipgrab/__init__.py
ipgrab/ipgrab.py
ipgrab-1.0.dist-info/METADATA
ipgrab-1.0.dist-info/RECORD
ipgrab-1.0.dist-info/WHEEL
ipgrab-1.0.dist-info/top_level.txt
